mupix/__init__.py
mupix/application.py
mupix/commands.py
mupix/core.py
mupix/extra.py
mupix/partwise.py
mupix/result_objects.py
mupix/sequence_alignment.py
mupix/typewise.py
mupix-0.3.1.dist-info/entry_points.txt
mupix-0.3.1.dist-info/LICENSE
mupix-0.3.1.dist-info/WHEEL
mupix-0.3.1.dist-info/METADATA
mupix-0.3.1.dist-info/RECORD
