Metadata-Version: 2.1
Name: mupix
Version: 0.3.1
Summary: MusicXML Evaluation Tool
License: GPL-3.0
Author: Deepio
Author-email: global2alex@gmail.com
Requires-Python: >=3.6,<4.0
Classifier: License :: OSI Approved :: GNU General Public License v3 (GPLv3)
Classifier: Programming Language :: Python :: 3
Classifier: Programming Language :: Python :: 3.6
Classifier: Programming Language :: Python :: 3.7
Classifier: Programming Language :: Python :: 3.8
Provides-Extra: docs
Requires-Dist: attrs (>=19.1,<20.0)
Requires-Dist: click (>=7.0,<8.0)
Requires-Dist: lxml (>=4.3,<5.0)
Requires-Dist: matplotlib (>=3.1,<4.0)
Requires-Dist: music21 (>=5.7,<6.0)
Requires-Dist: scipy (>=1.3,<2.0)
